NetLogoDOE/Gui.py
NetLogoDOE/__init__.py
NetLogoDOE/src/__init__.py
NetLogoDOE/src/gui/__init__.py
NetLogoDOE/src/gui/custom_components.py
NetLogoDOE/src/gui/custom_windows.py
NetLogoDOE/src/gui/help_dictionary.py
NetLogoDOE/src/gui/navigation/ExperimentResultsScreen.py
NetLogoDOE/src/gui/navigation/ExperimentScreen.py
NetLogoDOE/src/gui/navigation/ImportScreen.py
NetLogoDOE/src/gui/navigation/MainScreen.py
NetLogoDOE/src/gui/navigation/RunScreen.py
NetLogoDOE/src/gui/navigation/StandardResultsScreen.py
NetLogoDOE/src/gui/navigation/StandardScreen.py
NetLogoDOE/src/gui/navigation/__init__.py
NetLogoDOE/src/gui/plots/__init__.py
NetLogoDOE/src/gui/plots/experiment/ExperimentConfigTableScreen.py
NetLogoDOE/src/gui/plots/experiment/HeatmapScreen.py
NetLogoDOE/src/gui/plots/experiment/ParallelCoordinatesScreen.py
NetLogoDOE/src/gui/plots/experiment/ScatterplotScreen.py
NetLogoDOE/src/gui/plots/experiment/__init__.py
NetLogoDOE/src/gui/plots/standard/BoxplotScreen.py
NetLogoDOE/src/gui/plots/standard/DistributionplotScreen.py
NetLogoDOE/src/gui/plots/standard/HistogramScreen.py
NetLogoDOE/src/gui/plots/standard/StandardConfigTableScreen.py
NetLogoDOE/src/gui/plots/standard/TimeSeriesplotScreen.py
NetLogoDOE/src/gui/plots/standard/ViolinplotScreen.py
NetLogoDOE/src/gui/plots/standard/__init__.py
NetLogoDOE/src/util/Runner.py
NetLogoDOE/src/util/Sampler.py
NetLogoDOE/src/util/__init__.py
NetLogoDOE/src/util/config_dicts/__init__.py
NetLogoDOE/src/util/config_dicts/get_experiment_dict.py
NetLogoDOE/src/util/config_dicts/get_standard_dict.py
NetLogoDOE/src/util/connectors/__init__.py
NetLogoDOE/src/util/connectors/experimental_connector.py
NetLogoDOE/src/util/connectors/standard_connector.py
NetLogoDOE/src/util/data_processing/__init__.py
NetLogoDOE/src/util/data_processing/merge_experiment_data.py
NetLogoDOE/src/util/data_processing/merge_standard_data.py
NetLogoDOE-1.0.1.dist-info/LICENSE.txt
NetLogoDOE-1.0.1.dist-info/METADATA
NetLogoDOE-1.0.1.dist-info/WHEEL
NetLogoDOE-1.0.1.dist-info/top_level.txt
NetLogoDOE-1.0.1.dist-info/RECORD
